{
  "mongo" : {
    "url" : "MONGO_URL"
  },
  "redis" : {
    "host" : "REDIS_HOST",
    "port" : "PORT",
    "password" : "PASSWORD"
  },
  "passport" : {
    "facebookAuth" : {
      "clientID"      : "APP_ID",
      "clientSecret"  : "APP_SECRET",
      "callbackURL"   : "http://localhost:8000/auth/facebook/callback"
    },

    "twitterAuth" : {
      "consumerKey"       : "your-consumer-key-here",
      "consumerSecret"    : "your-client-secret-here",
      "callbackURL"       : "http://localhost:8080/auth/twitter/callback"
    },

    "googleAuth" : {
      "clientID"      : "your-secret-clientID-here",
      "clientSecret"  : "your-client-secret-here",
      "callbackURL"   : "http://localhost:8080/auth/google/callback"
    }

  }
}